{
    "dmFancyBetMarkets": [
        {
            "apiSiteEventId": 34807931,
            "apiSiteMarketId": "4.1759964383383-F2",
            "eventName": "India v West Indies",
            "marketName": "75 Over Run IND",
            "marketType": 1,
            "status": 2,
            "summaryStatus": 0,
            "gameOver": 0,
            "betAllowed": 1,
            "suspended": 0,
            "autoSuspended": 0,
            "ballRunning": 0,
            "closeSite": null,
            "sort": 3
        },
        {
            "apiSiteEventId": 34807931,
            "apiSiteMarketId": "4.1759964379833-F2",
            "eventName": "India v West Indies",
            "marketName": "Only 72 Over Run IND",
            "marketType": 1,
            "status": 2,
            "summaryStatus": 0,
            "gameOver": 0,
            "betAllowed": 1,
            "suspended": 1,
            "autoSuspended": 0,
            "ballRunning": 0,
            "closeSite": null,
            "sort": 2
        },
        {
            "apiSiteEventId": 34807931,
            "apiSiteMarketId": "4.1759964407261-F2",
            "eventName": "India v West Indies",
            "marketName": "3rd Wkt Pship Boundaries IND",
            "marketType": 1,
            "status": 2,
            "summaryStatus": 0,
            "gameOver": 0,
            "betAllowed": 1,
            "suspended": 1,
            "autoSuspended": 1,
            "ballRunning": 0,
            "closeSite": null,
            "sort": 9
        },
        {
            "apiSiteEventId": 34807931,
            "apiSiteMarketId": "4.1759964535602-F3",
            "eventName": "India v West Indies",
            "marketName": "3rd Wkt Caught Out IND",
            "marketType": 4,
            "status": 2,
            "summaryStatus": 0,
            "gameOver": 0,
            "betAllowed": 1,
            "suspended": 1,
            "autoSuspended": 0,
            "ballRunning": 0,
            "closeSite": null,
            "sort": 1
        },
        {
            "apiSiteEventId": 34807931,
            "apiSiteMarketId": "4.1759964379434-F2",
            "eventName": "India v West Indies",
            "marketName": "71 Over Run IND",
            "marketType": 1,
            "status": 2,
            "summaryStatus": 0,
            "gameOver": 0,
            "betAllowed": 1,
            "suspended": 1,
            "autoSuspended": 0,
            "ballRunning": 0,
            "closeSite": null,
            "sort": 3
        },
        {
            "apiSiteEventId": 34807931,
            "apiSiteMarketId": "4.1759964419298-F2",
            "eventName": "India v West Indies",
            "marketName": "Shubman Gill Runs",
            "marketType": 1,
            "status": 2,
            "summaryStatus": 0,
            "gameOver": 0,
            "betAllowed": 1,
            "suspended": 1,
            "autoSuspended": 0,
            "ballRunning": 0,
            "closeSite": null,
            "sort": 7
        },
        {
            "apiSiteEventId": 34807931,
            "apiSiteMarketId": "4.1759964419724-F2",
            "eventName": "India v West Indies",
            "marketName": "Shubman Gill Boundaries",
            "marketType": 1,
            "status": 2,
            "summaryStatus": 0,
            "gameOver": 0,
            "betAllowed": 1,
            "suspended": 1,
            "autoSuspended": 0,
            "ballRunning": 0,
            "closeSite": null,
            "sort": 8
        },
        {
            "apiSiteEventId": 34807931,
            "apiSiteMarketId": "4.1759964406879-F2",
            "eventName": "India v West Indies",
            "marketName": "Fall of 3rd Wkt IND",
            "marketType": 1,
            "status": 2,
            "summaryStatus": 0,
            "gameOver": 0,
            "betAllowed": 1,
            "suspended": 1,
            "autoSuspended": 0,
            "ballRunning": 0,
            "closeSite": null,
            "sort": 4
        },
        {
            "apiSiteEventId": 34807931,
            "apiSiteMarketId": "4.1759964537237-OE",
            "eventName": "India v West Indies",
            "marketName": "1st Ing 90 Over Odd Run Bhav (IND vs WI) Adv",
            "marketType": 5,
            "status": 2,
            "summaryStatus": 0,
            "gameOver": 0,
            "betAllowed": 1,
            "suspended": 0,
            "autoSuspended": 1,
            "ballRunning": 0,
            "closeSite": null,
            "sort": 0
        },
        {
            "apiSiteEventId": 34807931,
            "apiSiteMarketId": "4.1759964537199-OE",
            "eventName": "India v West Indies",
            "marketName": "1st Ing 80 Over Odd Run Bhav (IND vs WI) Adv",
            "marketType": 5,
            "status": 2,
            "summaryStatus": 0,
            "gameOver": 0,
            "betAllowed": 1,
            "suspended": 1,
            "autoSuspended": 0,
            "ballRunning": 0,
            "closeSite": null,
            "sort": 0
        },
        {
            "apiSiteEventId": 34807931,
            "apiSiteMarketId": "4.1759964380380-F2",
            "eventName": "India v West Indies",
            "marketName": "72 Over Run IND",
            "marketType": 1,
            "status": 2,
            "summaryStatus": 0,
            "gameOver": 0,
            "betAllowed": 1,
            "suspended": 1,
            "autoSuspended": 0,
            "ballRunning": 0,
            "closeSite": null,
            "sort": 3
        },
        {
            "apiSiteEventId": 34807931,
            "apiSiteMarketId": "4.1759964380783-F2",
            "eventName": "India v West Indies",
            "marketName": "Only 73 Over Run IND",
            "marketType": 1,
            "status": 1,
            "summaryStatus": 0,
            "gameOver": 0,
            "betAllowed": 1,
            "suspended": 1,
            "autoSuspended": 0,
            "ballRunning": 0,
            "closeSite": null,
            "sort": 2
        },
        {
            "apiSiteEventId": 34807931,
            "apiSiteMarketId": "4.1759964385563-F2",
            "eventName": "India v West Indies",
            "marketName": "Only 78 Over Run IND",
            "marketType": 1,
            "status": 2,
            "summaryStatus": 0,
            "gameOver": 0,
            "betAllowed": 1,
            "suspended": 1,
            "autoSuspended": 0,
            "ballRunning": 0,
            "closeSite": null,
            "sort": 2
        },
        {
            "apiSiteEventId": 34807931,
            "apiSiteMarketId": "4.1759964385120-F2",
            "eventName": "India v West Indies",
            "marketName": "77 Over Run IND",
            "marketType": 1,
            "status": 1,
            "summaryStatus": 0,
            "gameOver": 1,
            "betAllowed": 1,
            "suspended": 1,
            "autoSuspended": 1,
            "ballRunning": 0,
            "closeSite": null,
            "sort": 3
        },
        {
            "apiSiteEventId": 34807931,
            "apiSiteMarketId": "4.1759964387784-F2",
            "eventName": "India v West Indies",
            "marketName": "80 Over Run IND",
            "marketType": 1,
            "status": 2,
            "summaryStatus": 0,
            "gameOver": 0,
            "betAllowed": 1,
            "suspended": 1,
            "autoSuspended": 0,
            "ballRunning": 0,
            "closeSite": null,
            "sort": 3
        },
        {
            "apiSiteEventId": 34807931,
            "apiSiteMarketId": "4.1759964386579-F2",
            "eventName": "India v West Indies",
            "marketName": "Only 79 Over Run IND",
            "marketType": 1,
            "status": 1,
            "summaryStatus": 0,
            "gameOver": 0,
            "betAllowed": 1,
            "suspended": 1,
            "autoSuspended": 0,
            "ballRunning": 0,
            "closeSite": null,
            "sort": 2
        },
        {
            "apiSiteEventId": 34807931,
            "apiSiteMarketId": "4.1759964386157-F2",
            "eventName": "India v West Indies",
            "marketName": "78 Over Run IND",
            "marketType": 1,
            "status": 1,
            "summaryStatus": 0,
            "gameOver": 0,
            "betAllowed": 1,
            "suspended": 1,
            "autoSuspended": 0,
            "ballRunning": 0,
            "closeSite": null,
            "sort": 3
        },
        {
            "apiSiteEventId": 34807931,
            "apiSiteMarketId": "4.1759964384714-F2",
            "eventName": "India v West Indies",
            "marketName": "Only 77 Over Run IND",
            "marketType": 1,
            "status": 1,
            "summaryStatus": 0,
            "gameOver": 1,
            "betAllowed": 1,
            "suspended": 1,
            "autoSuspended": 0,
            "ballRunning": 0,
            "closeSite": null,
            "sort": 2
        },
        {
            "apiSiteEventId": 34807931,
            "apiSiteMarketId": "4.1759964387380-F2",
            "eventName": "India v West Indies",
            "marketName": "Only 80 Over Run IND",
            "marketType": 1,
            "status": 2,
            "summaryStatus": 0,
            "gameOver": 0,
            "betAllowed": 1,
            "suspended": 1,
            "autoSuspended": 0,
            "ballRunning": 0,
            "closeSite": null,
            "sort": 2
        },
        {
            "apiSiteEventId": 34807931,
            "apiSiteMarketId": "4.1759964386975-F2",
            "eventName": "India v West Indies",
            "marketName": "79 Over Run IND",
            "marketType": 1,
            "status": 2,
            "summaryStatus": 0,
            "gameOver": 0,
            "betAllowed": 1,
            "suspended": 1,
            "autoSuspended": 0,
            "ballRunning": 0,
            "closeSite": null,
            "sort": 3
        },
        {
            "apiSiteEventId": 34807931,
            "apiSiteMarketId": "4.1759964392440-F2",
            "eventName": "India v West Indies",
            "marketName": "Only 86 Over Run IND",
            "marketType": 1,
            "status": 2,
            "summaryStatus": 0,
            "gameOver": 0,
            "betAllowed": 1,
            "suspended": 1,
            "autoSuspended": 1,
            "ballRunning": 0,
            "closeSite": null,
            "sort": 2
        },
        {
            "apiSiteEventId": 34807931,
            "apiSiteMarketId": "4.1759964515778-F2",
            "eventName": "India v West Indies",
            "marketName": "3rd Wkt Pship Boundaries WI 2",
            "marketType": 1,
            "status": 2,
            "summaryStatus": 0,
            "gameOver": 0,
            "betAllowed": 1,
            "suspended": 0,
            "autoSuspended": 0,
            "ballRunning": 0,
            "closeSite": null,
            "sort": 9
        },
        {
            "apiSiteEventId": 34807931,
            "apiSiteMarketId": "4.1760300395515-OE",
            "eventName": "India v West Indies",
            "marketName": "60 Over Odd Run Bhav WI 2",
            "marketType": 5,
            "status": 2,
            "summaryStatus": 0,
            "gameOver": 0,
            "betAllowed": 1,
            "suspended": 0,
            "autoSuspended": 1,
            "ballRunning": 0,
            "closeSite": null,
            "sort": 0
        },
        {
            "apiSiteEventId": 34807931,
            "apiSiteMarketId": "4.1759964526300-F2",
            "eventName": "India v West Indies",
            "marketName": "John Campbell Boundaries 2",
            "marketType": 1,
            "status": 2,
            "summaryStatus": 0,
            "gameOver": 0,
            "betAllowed": 1,
            "suspended": 0,
            "autoSuspended": 0,
            "ballRunning": 0,
            "closeSite": null,
            "sort": 8
        },
        {
            "apiSiteEventId": 34807931,
            "apiSiteMarketId": "4.1759964526672-F2",
            "eventName": "India v West Indies",
            "marketName": "Shai Hope Runs 2",
            "marketType": 1,
            "status": 2,
            "summaryStatus": 0,
            "gameOver": 0,
            "betAllowed": 1,
            "suspended": 0,
            "autoSuspended": 0,
            "ballRunning": 0,
            "closeSite": null,
            "sort": 7
        },
        {
            "apiSiteEventId": 34807931,
            "apiSiteMarketId": "4.1759964537894-F3",
            "eventName": "India v West Indies",
            "marketName": "3rd Wkt Caught Out WI 2",
            "marketType": 4,
            "status": 2,
            "summaryStatus": 0,
            "gameOver": 0,
            "betAllowed": 1,
            "suspended": 0,
            "autoSuspended": 0,
            "ballRunning": 0,
            "closeSite": null,
            "sort": 1
        },
        {
            "apiSiteEventId": 34807931,
            "apiSiteMarketId": "4.1759964471285-F2",
            "eventName": "India v West Indies",
            "marketName": "50 Over Run WI 2",
            "marketType": 1,
            "status": 2,
            "summaryStatus": 0,
            "gameOver": 0,
            "betAllowed": 1,
            "suspended": 1,
            "autoSuspended": 1,
            "ballRunning": 0,
            "closeSite": null,
            "sort": 3
        },
        {
            "apiSiteEventId": 34807931,
            "apiSiteMarketId": "4.1759964527043-F2",
            "eventName": "India v West Indies",
            "marketName": "Shai Hope Boundaries 2",
            "marketType": 1,
            "status": 2,
            "summaryStatus": 0,
            "gameOver": 0,
            "betAllowed": 1,
            "suspended": 0,
            "autoSuspended": 0,
            "ballRunning": 0,
            "closeSite": null,
            "sort": 8
        },
        {
            "apiSiteEventId": 34807931,
            "apiSiteMarketId": "4.1759964525923-F2",
            "eventName": "India v West Indies",
            "marketName": "John Campbell Runs 2",
            "marketType": 1,
            "status": 2,
            "summaryStatus": 0,
            "gameOver": 0,
            "betAllowed": 1,
            "suspended": 0,
            "autoSuspended": 0,
            "ballRunning": 0,
            "closeSite": null,
            "sort": 7
        },
        {
            "apiSiteEventId": 34807931,
            "apiSiteMarketId": "4.1759964515394-F2",
            "eventName": "India v West Indies",
            "marketName": "Fall of 3rd Wkt WI 2",
            "marketType": 1,
            "status": 2,
            "summaryStatus": 0,
            "gameOver": 0,
            "betAllowed": 1,
            "suspended": 0,
            "autoSuspended": 0,
            "ballRunning": 0,
            "closeSite": null,
            "sort": 4
        },
        {
            "apiSiteEventId": 34807931,
            "apiSiteMarketId": "4.1759964472455-F2",
            "eventName": "India v West Indies",
            "marketName": "Only 52 Over Run WI 2",
            "marketType": 1,
            "status": 2,
            "summaryStatus": 0,
            "gameOver": 0,
            "betAllowed": 1,
            "suspended": 1,
            "autoSuspended": 1,
            "ballRunning": 0,
            "closeSite": null,
            "sort": 2
        },
        {
            "apiSiteEventId": 34807931,
            "apiSiteMarketId": "4.1759964472089-F2",
            "eventName": "India v West Indies",
            "marketName": "51 Over Run WI 2",
            "marketType": 1,
            "status": 2,
            "summaryStatus": 0,
            "gameOver": 0,
            "betAllowed": 1,
            "suspended": 0,
            "autoSuspended": 0,
            "ballRunning": 0,
            "closeSite": null,
            "sort": 3
        },
        {
            "apiSiteEventId": 34807931,
            "apiSiteMarketId": "4.1759964475141-F2",
            "eventName": "India v West Indies",
            "marketName": "55 Over Run WI 2",
            "marketType": 1,
            "status": 2,
            "summaryStatus": 0,
            "gameOver": 0,
            "betAllowed": 1,
            "suspended": 0,
            "autoSuspended": 0,
            "ballRunning": 0,
            "closeSite": null,
            "sort": 3
        },
        {
            "apiSiteEventId": 34807931,
            "apiSiteMarketId": "4.1760362046660-OE",
            "eventName": "India v West Indies",
            "marketName": "70 Over Odd Run Bhav WI 2",
            "marketType": 5,
            "status": 2,
            "summaryStatus": 0,
            "gameOver": 0,
            "betAllowed": 1,
            "suspended": 0,
            "autoSuspended": 1,
            "ballRunning": 0,
            "closeSite": null,
            "sort": 0
        }
    ],
    "dmFancyBetEvent": {
        "eventType": 4,
        "apiSiteEventId": 34807931,
        "eventName": "India v West Indies",
        "eventUpdateDate": 1760328091040,
        "closeSite": null,
        "mappingStatus": 1,
        "mappingUpdateDate": 1759966026078,
        "highlightMarketId": "1.248622840",
        "min": 1,
        "max": 9800,
        "limitUpdateDate": 1718870592266
    },
    "version": 1760328408122
}