{
    "match_api_id": "-53070",
    "match_title": "Chennai (V) v Bengaluru (V)",
    "sports_api_id": "2",
    "sports_category_name": "cricket",
    "tournament_api_id": "-1518",
    "tournament_name": "Virtual Turbo Classic",
    "start_time": "2025-10-01T09:51:00Z",
    "in_play": true,
    "bet_locked": true,
    "market": {
        "op": "Wickspin",
        "market_api_id": "-53425",
        "market_title": "Match Odds",
        "totalMatched": -1,
        "is_locked": false,
        "visible": true,
        "runners": []
    }
}