{
    "eventType": 2,
    "eventId": 34784953,
    "marketId": "1.248350000",
    "marketType": "MATCH_ODDS",
    "bettingType": 1,
    "countryCode": null,
    "marketName": "Match Odds",
    "status": 1,
    "summaryStatus": 0,
    "isHighLight": 1,
    "inPlay": 1,
    "totalMatched": 78672.17,
    "totalMatchedInUSD": 74266.53,
    "numberOfRunners": 2,
    "numberOfWinners": 1,
    "numberOfActiveRunners": 2,
    "marketTime": "2025-10-01 09:10",
    "marketTimeStr": "01 Oct, 09:10",
    "marketDateTime": 1759290000000,
    "openDateDayOfWeek": "Wed",
    "updateDate": "2025-10-01T12:21:20.039+0800",
    "version": 6893600385,
    "closeSite": null,
    "bookMode": null,
    "disableBettingSite": "",
    "autoDisableBettingSite": null,
    "isLowLiquidity": false,
    "isStreamingOpenTime": 1,
    "isCashOutMarket": true,
    "isUnmatchedModeMarket": false,
    "isToday": true,
    "betLimitSetting": {
        "minBet": 1.0,
        "maxBet": 50.0
    },
    "selections": [
        {
            "selectionId": 9631351,
            "runnerName": "Lucia Bronzetti",
            "sortPriority": 2,
            "status": 1,
            "updateDate": "2025-09-29T13:35:02.640+0800",
            "oddsUpdateDate": 1759292495890,
            "closeSite": "[\"0\", \"1\", \"2\", \"3\", \"4\", \"5\", \"6\", \"7\", \"8\", \"9\", \"10\", \"11\", \"12\", \"13\", \"14\", \"15\", \"16\", \"17\", \"18\", \"19\"]",
            "suspendSite": null,
            "bookMode": "[\"0\"]",
            "bookSuspend": null,
            "isAutoSuspend": false,
            "availableToBack": [
                {
                    "price": 5.0,
                    "size": 240.44
                },
                {
                    "price": 4.9,
                    "size": 6.76
                },
                {
                    "price": 4.8,
                    "size": 358.74
                }
            ],
            "availableToLay": [
                {
                    "price": 5.1,
                    "size": 6.45
                },
                {
                    "price": 5.2,
                    "size": 164.02
                },
                {
                    "price": 5.3,
                    "size": 95.41
                }
            ],
            "tradedVolume": []
        },
        {
            "selectionId": 11772894,
            "runnerName": "Joanna Garland",
            "sortPriority": 1,
            "status": 1,
            "updateDate": "2025-09-29T13:35:04.452+0800",
            "oddsUpdateDate": 1759292495890,
            "closeSite": "[\"0\", \"1\", \"2\", \"3\", \"4\", \"5\", \"6\", \"7\", \"8\", \"9\", \"10\", \"11\", \"12\", \"13\", \"14\", \"15\", \"16\", \"17\", \"18\", \"19\"]",
            "suspendSite": null,
            "bookMode": "[\"0\"]",
            "bookSuspend": null,
            "isAutoSuspend": false,
            "availableToBack": [
                {
                    "price": 1.24,
                    "size": 255.24
                },
                {
                    "price": 1.23,
                    "size": 2272.91
                },
                {
                    "price": 1.22,
                    "size": 31.49
                }
            ],
            "availableToLay": [
                {
                    "price": 1.25,
                    "size": 961.74
                },
                {
                    "price": 1.26,
                    "size": 756.21
                },
                {
                    "price": 1.27,
                    "size": 2659.12
                }
            ],
            "tradedVolume": []
        }
    ]
}